{"id": 1, "score": 3.0, "relevant": "No", "text": "Describe slate, phyllite, schist, and gneiss in terms of texture and grain size.", "common_words": 4, "features": [0.33, 0.0, 0, 1, 0.67, 0.0]}
{"id": 2, "score": 2.16, "relevant": "No", "text": "The parent rock of most hornfels is shale or another clay-rich rock, which has been \u201cbaked\u201d by a hot intruding magma body.", "common_words": 1, "features": [0.05, 0.0, 1, 1, 0.43, 0.0]}
{"id": 3, "score": 2.06, "relevant": "No", "text": "Write a description for each of these metamorphic environments: contact metamorphism, hydrothermal metamorphism, subduction zone metamorphism, and regional metamorphism. \n\n", "common_words": 0, "features": [0.0, 0.0, 0, 1, 0.53, 0.0]}
{"id": 4, "score": 1.92, "relevant": "No", "text": "We will consider the basic metamorphic environments\u2014contact or thermal metamorphism, hydrothermal metamorphism, burial and subduction zone metamorphism, and regional metamorphism\u2014as well as a few types of metamorphism that generate relatively small quantities of metamorphic rock. \n\n", "common_words": 1, "features": [0.03, 0.0, 0, 1, 0.43, 0.0]}
{"id": 5, "score": 1.78, "relevant": "No", "text": "Most of these environments occur in the vicinity of plate margins, and several are associated with igneous activity.", "common_words": 0, "features": [0.0, 0.0, 1, 1, 0.29, 0.0]}
{"id": 6, "score": 1.76, "relevant": "No", "text": "Briefly describe the appearance of the metamorphic rock gneiss and explain how it 4.", "common_words": 2, "features": [0.15, 0.0, 0, 1, 0.23, 0.0]}
{"id": 7, "score": 1.6, "relevant": "No", "text": "Hornfels tends to be gray to black in color and quite hard, and it may display conchoidal fracture. \n\n", "common_words": 1, "features": [0.06, 0.0, 0, 1, 0.24, 0.0]}
{"id": 8, "score": 0.66, "relevant": "No", "text": "This graph illustrates the temperatures and pressures typically associated with the major types of metamorphic environments.", "common_words": 0, "features": [0.0, 0.0, 0, 0, 0.33, 0.0]}
{"id": 9, "score": 0.0, "relevant": "No", "text": "Metamorphism occurs in many different environments.", "common_words": 0, "features": [0.0, 0.0, 0, 1, 0.17, 0.17]}
{"id": 10, "score": 0.0, "relevant": "No", "text": "Compare and contrast marble and quartzite. \n\n", "common_words": 0, "features": [0.0, 0.0, 0, 1, 0.5, 0.0]}
{"id": 11, "score": 0.0, "relevant": "No", "text": "5.", "common_words": 0, "features": [0.0, 0.0, 0, 1, 0.0, 0.0]}
{"id": 12, "score": 0.0, "relevant": "No", "text": "3.", "common_words": 0, "features": [0.0, 0.0, 0, 1, 0.0, 0.0]}
{"id": 13, "score": 0.0, "relevant": "No", "text": "In the rock mica schist, what does mica indicate, and what does schist indicate?", "common_words": 1, "features": [0.11, 0.0, 0, 1, 0.56, 0.0]}
{"id": 14, "score": 0.0, "relevant": "No", "text": "2.", "common_words": 0, "features": [0.0, 0.0, 0, 1, 0.0, 0.0]}
{"id": 15, "score": 0.0, "relevant": "No", "text": "Although slate and phyllite resemble each other, how can they be differentiated?", "common_words": 0, "features": [0.0, 0.0, 0, 0, 0.17, 0.0]}
{"id": 16, "score": 0.0, "relevant": "No", "text": "1.", "common_words": 0, "features": [0.0, 0.0, 0, 1, 0.0, 0.0]}
{"id": 17, "score": 0.0, "relevant": "No", "text": "Increase in and pressure variable mineral composition.", "common_words": 1, "features": [0.14, 0.0, 0, 1, 0.43, 0.0]}
