{"id": 1, "score": 2.74, "relevant": "Yes", "text": "These rocky materials were rich in oxygen and \u201coxygen-seeking\u201d elements, particularly silicon and aluminum, along with lesser amounts of calcium, sodium, potassium, iron, and magnesium.", "common_words": 10, "features": [0.62, 0.0, 0, 0, 0.75, 0.0]}
{"id": 2, "score": 2.5, "relevant": "No", "text": "If a bottle filled with clay, iron filings, water, and air were shaken, it would appear to have a single, muddy composition.", "common_words": 2, "features": [0.17, 0.0, 0, 1, 0.58, 0.0]}
{"id": 3, "score": 2.48, "relevant": "No", "text": "During this time of intense heating, Earth became hot enough that elements including iron and nickel began to melt.", "common_words": 3, "features": [0.27, 0.0, 0, 1, 0.45, 0.09]}
{"id": 4, "score": 2.2, "relevant": "No", "text": "The early period of heating resulted in another process of chemical differentiation, whereby melting formed masses of less-dense, molten rock that buoyantly rose toward the surface and solidified to produce a primitive crust.", "common_words": 3, "features": [0.15, 0.0, 0, 1, 0.45, 0.0]}
{"id": 5, "score": 2.12, "relevant": "No", "text": "As material accumulated to form Earth (and for a short period afterward), the high-velocity impact of nebular debris and the decay of radioactive elements caused the temperature of our planet to steadily increase.", "common_words": 2, "features": [0.1, 0.0, 0, 1, 0.45, 0.05]}
{"id": 6, "score": 1.8, "relevant": "No", "text": "Melting produced liquid blobs of heavy metal that gravitationally sank toward the center of the planet.", "common_words": 0, "features": [0.0, 0.0, 0, 1, 0.4, 0.0]}
{"id": 7, "score": 1.66, "relevant": "No", "text": "If that bottle were then allowed to sit undisturbed, the different materials would separate and settle into layers.", "common_words": 0, "features": [0.0, 0.0, 0, 1, 0.33, 0.0]}
{"id": 8, "score": 1.1, "relevant": "No", "text": "This process occurred rapidly on the scale of geologic time and produced Earth\u2019s dense iron-rich core.", "common_words": 2, "features": [0.15, 0.0, 0, 0, 0.38, 0.08]}
{"id": 9, "score": 0.0, "relevant": "No", "text": "Formation of Earth\u2019s Layered Structure", "common_words": 2, "features": [0.4, 0.0, 0, 1, 0.0, 0.8]}
{"id": 10, "score": 0.0, "relevant": "No", "text": "Earth\u2019s interior. \n\n", "common_words": 1, "features": [0.25, 0.0, 0, 1, 0.25, 0.25]}
{"id": 11, "score": 0.0, "relevant": "No", "text": "The force of gravity is responsible for the layering in the bottle of muddy water, as well as the layering we detect in", "common_words": 0, "features": [0.0, 0.0, 0, 1, 0.75, 0.0]}
{"id": 12, "score": 0.0, "relevant": "No", "text": "Above the iron would be a layer of clay, then water, and, finally, air.", "common_words": 1, "features": [0.17, 0.0, 0, 0, 0.83, 0.0]}
{"id": 13, "score": 0.0, "relevant": "No", "text": "The iron filings, which are the densest, would be the first to sink to the bottom.", "common_words": 1, "features": [0.25, 0.0, 1, 1, 0.75, 0.0]}
